dnsearch/__init__.py
dnsearch/attribute.py
dnsearch/command.py
dnsearch-0.1a1.dist-info/LICENSE
dnsearch-0.1a1.dist-info/METADATA
dnsearch-0.1a1.dist-info/WHEEL
dnsearch-0.1a1.dist-info/entry_points.txt
dnsearch-0.1a1.dist-info/top_level.txt
dnsearch-0.1a1.dist-info/zip-safe
dnsearch-0.1a1.dist-info/RECORD
